debu/__init__.py
debu/cp.py
debu/execute.py
debu/interpreter.py
debu/ssh.py
debu-0.1.0.dist-info/METADATA
debu-0.1.0.dist-info/RECORD
debu-0.1.0.dist-info/WHEEL
debu-0.1.0.dist-info/entry_points.txt
debu-0.1.0.dist-info/top_level.txt
