Metadata-Version: 2.1
Name: debu
Version: 0.1.0
Summary: Automatic Deployment and Build tool
Home-page: https://github.com/SiLeader/debu
Author: SiLeader
Author-email: 
License: Apache License 2.0
Platform: UNKNOWN
Classifier: Development Status :: 4 - Beta
Classifier: Intended Audience :: Developers
Classifier: Intended Audience :: System Administrators
Classifier: License :: OSI Approved
Classifier: License :: OSI Approved :: Apache Software License
Classifier: Topic :: Software Development
Classifier: Topic :: Software Development :: Build Tools
Classifier: Topic :: Software Development :: Interpreters
Classifier: Topic :: System
Classifier: Topic :: System :: Installation/Setup
Requires-Python: >=3.5
Requires-Dist: asn1crypto (==0.24.0)
Requires-Dist: bcrypt (==3.1.4)
Requires-Dist: cffi (==1.11.5)
Requires-Dist: cryptography (==2.3)
Requires-Dist: idna (==2.7)
Requires-Dist: paramiko (==2.4.1)
Requires-Dist: pyasn1 (==0.4.4)
Requires-Dist: pycparser (==2.18)
Requires-Dist: PyNaCl (==1.2.1)
Requires-Dist: six (==1.11.0)
